totui/__init__.py
totui/coins.list
totui/config.ini
totui/logo.uni
totui/totui.py
totui/coinimg/ACM.png
totui/coinimg/ADA.png
totui/coinimg/AEON.png
totui/coinimg/ARQ.png
totui/coinimg/ARRR.png
totui/coinimg/AVN.png
totui/coinimg/BBS.png
totui/coinimg/BCN.png
totui/coinimg/BEAM.png
totui/coinimg/BITC.png
totui/coinimg/BKC.png
totui/coinimg/BLKC.png
totui/coinimg/BLOC.png
totui/coinimg/BTC.png
totui/coinimg/BTCP.png
totui/coinimg/BTCZ.png
totui/coinimg/CASH.png
totui/coinimg/CCX.png
totui/coinimg/CIV.png
totui/coinimg/CLOAK.png
totui/coinimg/COAL.png
totui/coinimg/CUT.png
totui/coinimg/D.png
totui/coinimg/DASH.png
totui/coinimg/DERO.png
totui/coinimg/DOGE.png
totui/coinimg/ERG.png
totui/coinimg/ETH.png
totui/coinimg/ETN.png
totui/coinimg/ETNX.png
totui/coinimg/ETNXP.png
totui/coinimg/FBF.png
totui/coinimg/FIRO.png
totui/coinimg/FLUX.png
totui/coinimg/GHOST.png
totui/coinimg/GPKR.png
totui/coinimg/GRFT.png
totui/coinimg/GRIMM.png
totui/coinimg/GRIN.png
totui/coinimg/GRLC.png
totui/coinimg/HUSH.png
totui/coinimg/INC.png
totui/coinimg/INTU.png
totui/coinimg/IRD.png
totui/coinimg/KDA.png
totui/coinimg/KRB.png
totui/coinimg/LNS.png
totui/coinimg/LTC.png
totui/coinimg/LTHN.png
totui/coinimg/LUX.png
totui/coinimg/MAT.png
totui/coinimg/MSR.png
totui/coinimg/MWC.png
totui/coinimg/NAH.png
totui/coinimg/NBR.png
totui/coinimg/NCP.png
totui/coinimg/OBTC.png
totui/coinimg/OMB.png
totui/coinimg/ONION.png
totui/coinimg/OXEN.png
totui/coinimg/PCN.png
totui/coinimg/PIVX.png
totui/coinimg/PLURA.png
totui/coinimg/POT.png
totui/coinimg/PRCY.png
totui/coinimg/PURK.png
totui/coinimg/QTUM.png
totui/coinimg/QUAN.png
totui/coinimg/RTM.png
totui/coinimg/RTO.png
totui/coinimg/RVN.png
totui/coinimg/RYO.png
totui/coinimg/SCP.png
totui/coinimg/SHB.png
totui/coinimg/SIN.png
totui/coinimg/SLD.png
totui/coinimg/SOLACE.png
totui/coinimg/SUMO.png
totui/coinimg/SYFR.png
totui/coinimg/TRTL.png
totui/coinimg/TUBE.png
totui/coinimg/UFO.png
totui/coinimg/UNI.png
totui/coinimg/UPX.png
totui/coinimg/USDT.png
totui-1.9.1.dist-info/LICENSE
totui-1.9.1.dist-info/METADATA
totui-1.9.1.dist-info/WHEEL
totui-1.9.1.dist-info/entry_points.txt
totui-1.9.1.dist-info/top_level.txt
totui-1.9.1.dist-info/RECORD
