Metadata-Version: 2.1
Name: totui
Version: 1.9.1
Summary: TradeOgre TUI
Home-page: https://github.com/protomens/totui
Author: protomens
Author-email: protomens@eratosthen.es
License: MIT
Keywords: crypto tui tradeogre bitcoin monero haven dero arrr
Classifier: Programming Language :: Python
Classifier: Programming Language :: Python :: 3
License-File: LICENSE
Requires-Dist: requests
Requires-Dist: npyscreen
Requires-Dist: undetected-chromedriver
Requires-Dist: selenium ==4.12.0
Requires-Dist: bs4
Requires-Dist: urllib3
Requires-Dist: pillow
Requires-Dist: qrcode
